odoo/addons/purchase_order_type_dashboard/README.rst
odoo/addons/purchase_order_type_dashboard/__init__.py
odoo/addons/purchase_order_type_dashboard/__manifest__.py
odoo/addons/purchase_order_type_dashboard/i18n/es.po
odoo/addons/purchase_order_type_dashboard/i18n/purchase_order_type_dashboard.pot
odoo/addons/purchase_order_type_dashboard/models/__init__.py
odoo/addons/purchase_order_type_dashboard/models/purchase_order_type.py
odoo/addons/purchase_order_type_dashboard/readme/CONTRIBUTORS.rst
odoo/addons/purchase_order_type_dashboard/readme/DESCRIPTION.rst
odoo/addons/purchase_order_type_dashboard/static/description/icon.png
odoo/addons/purchase_order_type_dashboard/static/description/index.html
odoo/addons/purchase_order_type_dashboard/tests/__init__.py
odoo/addons/purchase_order_type_dashboard/tests/test_purchase_order_type_dashboard.py
odoo/addons/purchase_order_type_dashboard/views/menu_purchase_order.xml
odoo/addons/purchase_order_type_dashboard/views/view_purchase_order.xml
odoo/addons/purchase_order_type_dashboard/views/view_purchase_order_type.xml
odoo13_addon_purchase_order_type_dashboard-13.0.1.0.1.dev6.dist-info/METADATA
odoo13_addon_purchase_order_type_dashboard-13.0.1.0.1.dev6.dist-info/WHEEL
odoo13_addon_purchase_order_type_dashboard-13.0.1.0.1.dev6.dist-info/top_level.txt
odoo13_addon_purchase_order_type_dashboard-13.0.1.0.1.dev6.dist-info/RECORD
